transcript_kit/__init__.py
transcript_kit/ai_client.py
transcript_kit/cli.py
transcript_kit/config.py
transcript_kit/processor.py
transcript_kit/utils.py
transcript_kit-0.1.1.dist-info/licenses/LICENSE
transcript_kit-0.1.1.dist-info/METADATA
transcript_kit-0.1.1.dist-info/WHEEL
transcript_kit-0.1.1.dist-info/entry_points.txt
transcript_kit-0.1.1.dist-info/top_level.txt
transcript_kit-0.1.1.dist-info/RECORD
