Metadata-Version: 2.4
Name: transcript-kit
Version: 0.1.1
Summary: AI-powered YouTube transcript processor
Author: Kevin Callens
License: MIT
Project-URL: Homepage, https://github.com/kevincallens/transcript-kit
Project-URL: Repository, https://github.com/kevincallens/transcript-kit
Project-URL: Issues, https://github.com/kevincallens/transcript-kit/issues
Keywords: youtube,transcript,ai,openrouter,subtitles
Classifier: Development Status :: 4 - Beta
Classifier: Intended Audience :: Developers
Classifier: Intended Audience :: End Users/Desktop
Classifier: License :: OSI Approved :: MIT License
Classifier: Programming Language :: Python :: 3
Classifier: Programming Language :: Python :: 3.8
Classifier: Programming Language :: Python :: 3.9
Classifier: Programming Language :: Python :: 3.10
Classifier: Programming Language :: Python :: 3.11
Classifier: Programming Language :: Python :: 3.12
Classifier: Operating System :: OS Independent
Classifier: Topic :: Multimedia :: Video
Classifier: Topic :: Text Processing
Requires-Python: >=3.8
License-File: LICENSE
Requires-Dist: requests>=2.28.0
Requires-Dist: urllib3<2.0.0,>=1.26.0
Requires-Dist: click>=8.0.0
Requires-Dist: pyyaml>=6.0
Requires-Dist: platformdirs>=3.0.0
Requires-Dist: yt-dlp>=2023.0.0
Provides-Extra: dev
Requires-Dist: pytest>=7.0.0; extra == "dev"
Requires-Dist: black>=22.0.0; extra == "dev"
Requires-Dist: ruff>=0.0.250; extra == "dev"
Dynamic: license-file
